MANIFEST.in
README.md
VERSION
setup.py
euganke_latex_importer.egg-info/PKG-INFO
euganke_latex_importer.egg-info/SOURCES.txt
euganke_latex_importer.egg-info/dependency_links.txt
euganke_latex_importer.egg-info/entry_points.txt
euganke_latex_importer.egg-info/not-zip-safe
euganke_latex_importer.egg-info/requires.txt
euganke_latex_importer.egg-info/top_level.txt
importer/__init__.py
importer/restapi.py
importer/bober/BoberParser.py
importer/bober/Main.py
importer/bober/__init__.py
importer/latex/Common.py
importer/latex/FAPPLatexParser.py
importer/latex/FAPPMain.py
importer/latex/PresekLatexParser.py
importer/latex/REPLatexParser.py
importer/latex/__init__.py
importer/moodle/Main.py
importer/moodle/MoodleParser.py
importer/moodle/__init__.py