Metadata-Version: 1.1
Name: euganke-latex-importer
Version: 0.1
Summary: euganke importer
Home-page: UNKNOWN
Author: Jaka Hudoklin
Author-email: jakahudoklin@gmail.com
License: UNKNOWN
Keywords: web wsgi bfg pylons pyramid
Platform: UNKNOWN
Classifier: Programming Language :: Python
Classifier: Topic :: Internet :: WWW/HTTP
